<Properties StartupConfiguration="{33A4C66E-6332-451E-9624-8D6D58A6E51F}|HubUfpr.NetCore">
  <MonoDevelop.Ide.Workbench ActiveDocument="Data/DapperORM/Class/UserRepository.cs">
    <Files>
      <File FileName="Service/Class/UserService.cs" Line="27" Column="1" />
      <File FileName="../../../Library/Caches/VisualStudio/8.0/Symbols/StackExchange/Dapper/247e498f0e52c88d0c58c6f1fa50457bb6ab5888/Dapper/SqlMapper.cs" Line="1051" Column="1" />
      <File FileName="Service/Interface/IUserService.cs" Line="1" Column="1" />
      <File FileName="Data/DapperORM/Class/UserRepository.cs" Line="14" Column="134" />
      <File FileName="Model/User.cs" Line="15" Column="28" />
    </Files>
    <Pads>
      <Pad Id="ProjectPad">
        <State name="__root__">
          <Node name="HubUfpr.NetCore" expanded="True">
            <Node name="HubUfpr.API" expanded="True">
              <Node name="Controllers" expanded="True" />
            </Node>
            <Node name="HubUfpr.Data" expanded="True">
              <Node name="DapperORM" expanded="True">
                <Node name="Class" expanded="True">
                  <Node name="UserRepository.cs" selected="True" />
                </Node>
              </Node>
            </Node>
            <Node name="HubUfpr.Model" expanded="True" />
            <Node name="HubUfpr.Service" expanded="True">
              <Node name="Interface" expanded="True" />
            </Node>
            <Node name="HubUfpr.Utils" expanded="True">
              <Node name="Dependencies" expanded="True" />
            </Node>
          </Node>
        </State>
      </Pad>
    </Pads>
  </MonoDevelop.Ide.Workbench>
  <MonoDevelop.Ide.ItemProperties.HubUfpr.API PreferredExecutionTarget="/Applications/Google Chrome.app" />
  <MonoDevelop.Ide.DebuggingService.PinnedWatches />
  <MonoDevelop.Ide.Workspace ActiveConfiguration="Debug" />
  <MonoDevelop.Ide.DebuggingService.Breakpoints>
    <BreakpointStore />
  </MonoDevelop.Ide.DebuggingService.Breakpoints>
  <MultiItemStartupConfigurations />
</Properties>