<Properties StartupConfiguration="{33A4C66E-6332-451E-9624-8D6D58A6E51F}|HubUfpr.NetCore">
  <MonoDevelop.Ide.Workbench ActiveDocument="Data/DapperORM/Class/BaseRepository.cs">
    <Files>
      <File FileName="Data/DapperORM/Class/BaseRepository.cs" Line="30" Column="1" />
      <File FileName="Service/Class/UserService.cs" Line="29" Column="1" />
      <File FileName="HubUfpr.NetCore/Controllers/CadastroController.cs" Line="1" Column="1" />
      <File FileName="HubUfpr.NetCore/Controllers/UserController.cs" Line="30" Column="24" />
    </Files>
    <Pads>
      <Pad Id="ProjectPad">
        <State name="__root__">
          <Node name="HubUfpr.NetCore" expanded="True">
            <Node name="HubUfpr.API" expanded="True">
              <Node name="Controllers" expanded="True" />
              <Node name="Properties" expanded="True" />
              <Node name="Requests" expanded="True" />
            </Node>
            <Node name="HubUfpr.Data" expanded="True">
              <Node name="DapperORM" expanded="True">
                <Node name="Class" expanded="True">
                  <Node name="BaseRepository.cs" selected="True" />
                </Node>
              </Node>
            </Node>
            <Node name="HubUfpr.Service" expanded="True">
              <Node name="Class" expanded="True" />
              <Node name="Interface" expanded="True" />
            </Node>
          </Node>
        </State>
      </Pad>
    </Pads>
  </MonoDevelop.Ide.Workbench>
  <MonoDevelop.Ide.ItemProperties.HubUfpr.API PreferredExecutionTarget="/Applications/Google Chrome.app" />
  <MonoDevelop.Ide.DebuggingService.PinnedWatches />
  <MonoDevelop.Ide.Workspace ActiveConfiguration="Debug" />
  <MonoDevelop.Ide.DebuggingService.Breakpoints>
    <BreakpointStore>
      <Breakpoint file="/Users/an20184783/Documents/tcc/HUB-Backend/Service/Class/UserService.cs" relfile="Service/Class/UserService.cs" line="29" column="1" />
      <Breakpoint file="/Users/an20184783/Documents/tcc/HUB-Backend/Data/DapperORM/Class/BaseRepository.cs" relfile="Data/DapperORM/Class/BaseRepository.cs" line="27" column="1" />
    </BreakpointStore>
  </MonoDevelop.Ide.DebuggingService.Breakpoints>
  <MultiItemStartupConfigurations />
</Properties>